{
  "1": {
    "rows": [
      "Republican Party",
      "Served in Military",
      "Democratic Party"
    ],
    "columns": [
      "Cold War President",
      "First Name Starts with A–J",
      "Served more than 5 years"
    ]
  },
  "2": {
    "rows": [
      "Democratic Party",
      "Served in Congress",
      "Impeached"
    ],
    "columns": [
      "Born 1900–2000",
      "First Name Starts with A–J",
      "Served less than 5 years"
    ]
  },
"3": {
  "rows": [
    "Republican Party",
    "Served in the House",
    "Born before 1800"
  ],
  "columns": [
    "Inaugurated older than 50",
    "Last Name K–Z",
    "Died in Office"
  ]
},
  "4": {
    "rows": [
      "Democratic Party",
      "Born 1900–2000",
      "First Name Starts with A–J"
    ],
    "columns": [
      "Nobel Prize Winner",
      "Attended Ivy League School",
      "Former State Governors"
    ]
  },
  "5": {
    "rows": [
      "Born 1800 - 1900",
      "Born before 1800",
      "Born 1900–2000"
    ],
    "columns": [
      "Served in Congress",
      "Died in Office",
      "Served as Vice President"
    ]
  },
  "6": {
    "rows": [
      "Appears On Currency",
      "Served more than 5 years",
      "Inaugurated older than 60"
    ],
    "columns": [
      "Served in Military",
      "Served as Vice President",
      "Served in Congress"
    ]
  },
  "7": {
    "rows": [
      "Republican Party",
      "Last Name K–Z",
      "Won Re-election"
    ],
    "columns": [
      "Served Past 1850",
      "Won Without Popular Vote",
      "First Name Starts with A–J"
    ]
  },
  "8": {
    "rows": [
      "Democratic Party",
      "Served more than 5 years",
      "Former State Governors"
    ],
    "columns": [
      "Born 1900–2000",
      "First Name Starts with A–J",
      "Attended Ivy League School"
    ]
  },
  "9": {
    "rows": [
      "Republican Party",
      "Served in Military",
      "Born 1800 - 1900"
    ],
    "columns": [
      "Served in Congress",
      "Last Name K–Z",
      "Won Re-election"
    ]
  },
  "10": {
    "rows": [
      "Democratic Party",
      "Served less than 5 years",
      "Republican Party"
    ],
    "columns": [
      "Born 1900–2000",
      "Cold War President",
      "Died in Office"
    ]
  },
  "11": {
    "rows": [
      "Republican Party",
      "Served more than 5 years",
      "Won Re-election"
    ],
    "columns": [
      "First Name Starts with A–J",
      "Served as Vice President",
      "Born 1900-2000"
    ]
  },
  "12": {
    "rows": [
      "First Name Starts with A–J",
      "Served in Congress",
      "Attended Ivy League School"
    ],
    "columns": [
      "Republican Party",
      "Born 1800 - 1900",
      "Last Name K–Z"
    ]
  },
  "13": {
    "rows": [
      "Republican Party",
      "Served in Military",
      "Born before 1800"
    ],
    "columns": [
      "Served less than 5 years",
      "Won Re-election",
      "First Name Starts with A–J"
    ]
  },
  "14": {
    "rows": [
      "Democratic Party",
      "Republican Party",
      "Last Name A–J"
    ],
    "columns": [
      "Served Past 1900",
      "Served in Congress",
      "Served as Vice President"
    ]
  },
  "15": {
    "rows": [
      "Democratic-republican Party",
      "Served in Congress",
      "First Name Starts with K–Z"
    ],
    "columns": [
      "Appears on Currency",
      "Served in Military",
      "Served more than 5 years"
    ]
  },
  "16": {
    "rows": [
      "Democratic Party",
      "Republican Party",
      "First Name Starts with A–J"
    ],
    "columns": [
      "Served in the senate",
      "Served in Congress",
      "Served in the House"
    ]
  },
  "17": {
    "rows": [
      "Born in Virginia",
      "Served more than 5 years",
      "Last Name A–J"
    ],
    "columns": [
      "Appears On Currency",
      "Born before 1800",
      "Served in Military"
    ]
  },
  "18": {
    "rows": [
      "Assassinated",
      "Inaugurated older than 50",
      "Democratic Party"
    ],
    "columns": [
      "First Name Starts with A–J",
      "First Name Starts with K–Z",
      "Last Name A–J"
    ]
  },
  "19": {
    "rows": [
      "Appears on Mount Rushmore",
      "Inaugurated older than 50",
      "Served in Congress"
    ],
    "columns": [
    "Born before 1800",
    "Born 1800 - 1900",
    "Republican Party"
    ]
  },
  "20": {
    "rows": [
      "Presidency Number 11-20",
      "Presidency Number 21-30",
      "Presidency Number 31-40"
    ],
    "columns": [
    "Republican Party",
    "Democratic Party",
    "Last Name A–J"
    ]
  },
  "21": {
    "rows": [
      "Served as Vice President",
      "Served more than 5 years",
      "Won Without Popular Vote"
    ],
    "columns": [
    "Served Past 1900",
    "Served Before 1900",
    "First Name Starts with A–J"
    ]
  },
  "22": {
    "rows": [
      "Former State Governors",
            "Served in Congress",
      "Served less than 5 years"
    ],
    "columns": [
      "Inaugurated older than 50",
      "Democratic Party",
      "Last Name K–Z"
    ]
  },
  "23": {
    "rows": [
      "Nobel Prize Winner",
      "Won Re-election",
      "Died in Office"
    ],
    "columns": [
      "Democratic Party",
    "Last Name A–J",
    "Served Past 1850"
    ]
  },
  "24": {
    "rows": [
      "Last Name A–J",
      "Last Name K–Z",
      "Served as Vice President"
    ],
    "columns": [
      "First Name Starts with A–J",
    "First Name Starts with K–Z",
    "Born 1900–2000"
    ]
  },
  "25": {
    "rows": [
    "Born before 1800",
    "Born 1800 - 1900",
     "First Name Starts with Vowel"
    ],
    "columns": [
      "Democratic Party",
    "Won Re-election",
    "Served in Military"
    ]
  },
  "26": {
    "rows": [
      "Inaugurated older than 60",
      "Born 1900-2000",
     "Last Name Starts with Vowel"
    ],
    "columns": [
      "Met Queen Elizabeth II",
    "Lost Re-election",
    "Served in Military"
    ]
  },
  "27": {
    "rows": [
      "6 feet or taller",
      "Shorter than 6 feet",
     "Attended Ivy League School"
    ],
    "columns": [
      "Democratic Party",
    "Republican Party",
      "Served more than 5 years"
    ]
  },
  "28": {
    "rows": [
      "Does Not Appear on Currency",
      "Did Not Win Nobel Prize",
      "Not Cold War President"
    ],
    "columns": [
     "Did not Serve as Vice President",
      "Did Not Die in Office",
      "Does Not Appear on Mount Rushmore"
    ]
  },
  "29": {
    "rows": [
      "No College Degree",
      "Attended Ivy League School",
      "Served in Congress"
    ],
    "columns": [
      "Presidency Number 1-10",
      "First Name Starts with A–J",
      "First Name Starts with K–Z"
    ]
  },
  "30": {
    "rows": [
      "180 Pounds or greater",
      "Less than 180 Pounds",
      "Appears On Currency"
    ],
    "columns": [
      "Democratic Party",
      "Republican Party",
      "Inaugurated older than 50"
    ]
  },
  "31": {
    "rows": [
      "Born in Virginia",
      "Served in the senate",
      "Inaugurated older than 55"
    ],
    "columns": [
      "Democratic-republican Party",
      "Died in Office",
      "Served less than 5 years"
    ]
  },
  "32": {
    "rows": [
      "Democratic Party",
      "Born before 1800",
      "Last Name A–J"
    ],
    "columns": [
      "Unmarried while in Office",
      "6 feet or taller",
      "Served in Congress"
    ]
  },
  "33": {
    "rows": [
      "Born in Ohio",
      "Assassinated",
      "Republican Party"
    ],
    "columns": [
      "Presidency Number 21-30",
      "Won Re-election",
      "Not Re-elected"
    ]
  },
  "34": {
    "rows": [
     "Served as Secretary of State",
     "Served as Vice President",
     "Served in Military"
    ],
    "columns": [
      "Founding Father",
      "Presidency Number 5-15",
      "First Name Starts with A–J"
    ]
  },
  "35": {
    "rows": [
     "Has Facial Hair",
       "Impeached",
       "Former State Governors"
    ],
    "columns": [
      "Served Before 1900",
      "200 Pounds or greater",
      "Served more than 5 years"
    ]
  },
  "36": {
    "rows": [
      "Whig Party",
      "Democratic Party",
      "Served in Congress"
    ],
    "columns": [
      "Inaugurated older than 50",
      "Tied to War of 1812",
      "Served less than 4 years"
    ]
  },
  "37": {
    "rows": [
      "Related to Another President",
      "Republican Party",
      "Served in the senate"
    ],
    "columns": [
     "Last Name Starts with Vowel",
      "Died in Office",
      "Presidency Number 40-47"
    ]
  },
  "38": {
    "rows": [
      "Alliterative name",
      "Served in the House",
      "Nobel Prize Winner"
    ],
    "columns": [
      "Born 1800 - 1900",
      "Born 1900–2000",
      "Not Assassinated"
    ]
  },
  "39": {
    "rows": [
      "Wore Glasses",
      "Inaugurated older than 60",
      "Attended Ivy League School"
    ],
    "columns": [
      "Cold War President",
      "Born 1800 - 1900",
      "Won Re-election"
    ]
  },
  "40": {
    "rows": [
      "Served as ambassador",
      "No College Degree",
      "Not impeached"
    ],
    "columns": [
      "Appears on Mount Rushmore",
      "Presidency Number 1-10",
      "First Name Starts with A–J"
    ]
  },
  "41": {
  "rows": [
    "6 feet or taller",
    "Served as Vice President",
    "Not Founding Father"
  ],
  "columns": [
    "First Name Starts with A–J",
    "Republican Party",
    "Appears On Currency"
  ]
},
"42": {
  "rows": [
    "Attended Ivy League School",
    "Served in the Senate",
    "Alliterative name"
  ],
  "columns": [
      "Won Re-election",
      "Democratic Party",
    "Did not serve in the Military"
  ]
},
"43": {
  "rows": [
    "Cold War President",
    "Last Name K–Z",
    "Died in Office"
  ],
  "columns": [
    "First Name Starts with K–Z",
    "Served in Congress",
    "Lost Re-election"
  ]
},
"44": {
  "rows": [
    "First Name Starts with A–J",
"Related to Another President",
    "Served as Secretary of State"
  ],
  "columns": [
    "Inaugurated older than 55",
    "Shorter than 6 feet",
    "Born before 1800"
  ]
},
"45": {
  "rows": [
    "Served in the House",
    "Served in the Senate",
"Presidency Number 31-40"
  ],
  "columns": [
    "Born 1800 - 1900",
    "Last Name Starts with Vowel",
    "Met Queen Elizabeth II"
  ]
},
"46": {
  "rows": [
    "Won Re-election",
    "Served in the House",
    "Served in the Military"
  ],
  "columns": [
    "Born 1900–2000",
    "Republican Party",
    "Assassinated"
  ]
},
"47": {
  "rows": [
    "Unmarried while in Office",
    "Tied to War of 1812",
    "Related to Another President"
  ],
  "columns": [
    "First Name Starts with A–J",
    "Shorter than 6 feet",
"First Name Starts with K–Z"
  ]
},
"48": {
  "rows": [
    "Cold War President",
    "Served as Vice President",
"No College Degree"
  ],
  "columns": [
"Met Queen Elizabeth II",
    "Won Re-election",
"Democratic Party"
  ]
},
"49": {
  "rows": [
    "Founding Father",
    "Served as Vice President",
    "Democratic-republican Party"
  ],
  "columns": [
    "Served in Congress",
    "Attended Ivy League School",
    "Born before 1800"
  ]
},
"50": {
  "rows": [
"Has Facial Hair",
"180 Pounds or greater",
"Less than 180 Pounds"
  ],
  "columns": [
"Presidency Number 21-30",
    "Served in the Military",
    "First Name Starts with A–J"
  ]
},
"51": {
  "rows": [
"Last Name K–Z",
    "Appears On Mount Rushmore",
    "Shorter than 6 feet"
  ],
  "columns": [
"Republican Party",
"Wore Glasses",
"No Biological Children"
  ]
},
"52": {
  "rows": [
"Did Not Win Nobel Prize",
"Born 1800 - 1900",
"Born 1900-2000"
  ],
  "columns": [
    "First Name Starts with K–Z",
    "Won without Popular Vote",
    "Assassinated"
  ]
},
"53": {
  "rows": [
    "6 feet or taller",
"Did not Attend Ivy League School",
"Democratic Party"
  ],
  "columns": [
    "Served in the Senate",
    "Served as Vice President",
    "Related to Another President"
  ]
},
"54": {
  "rows": [
    "Appears On Currency",
    "Won Re-election",
"Born in Ohio or Virginia"
  ],
  "columns": [
    "Born before 1800",
    "Served in the Military",
"Tied to Civil War"
  ]
},
"55": {
  "rows": [
    "No Biological Children",
    "Died in Office",
    "Shorter than 6 feet"
  ],
  "columns": [
    "Political Party: Republican",
    "Served as Secretary of State",
    "Cold War President"
  ]
},
"56": {
  "rows": [
    "Tied to War of 1812",
    "Served in the Senate",
    "Assassinated"
  ],
  "columns": [
    "First Name Starts with A–J",
    "Born 1800–1900",
    "Appears On Mount Rushmore"
  ]
},
"57": {
  "rows": [
    "Served as Vice President",
    "Met Queen Elizabeth II",
    "6 feet or taller"
  ],
  "columns": [
    "Political Party: Democratic",
    "Won without Popular Vote",
    "No Biological Children"
  ]
},
"58": {
  "rows": [
    "Alliterative name",
    "Served in the House",
    "Cold War President"
  ],
  "columns": [
    "Born 1900–2000",
    "Served in the Military",
    "Appears On Currency"
  ]
},
"59": {
  "rows": [
    "Attended Ivy League School",
    "Unmarried while in Office",
    "Appears On Mount Rushmore"
  ],
  "columns": [
    "First Name Starts with K–Z",
    "Shorter than 6 feet",
    "Won Re-election"
  ]
},
"60": {
  "rows": [
    "Served in the House",
    "6 feet or taller",
    "Died in Office"
  ],
  "columns": [
    "Political Party: Republican",
    "Founding Father",
    "Related to Another President"
  ]
}
      }
    

